setup.py
ankitpackage/__init__.py
ankitpackage/utilities.py
ankitpackage.egg-info/PKG-INFO
ankitpackage.egg-info/SOURCES.txt
ankitpackage.egg-info/dependency_links.txt
ankitpackage.egg-info/not-zip-safe
ankitpackage.egg-info/top_level.txt