Metadata-Version: 1.0
Name: ankitpackage
Version: 0.1
Summary: First python package
Home-page: http://github.com/storborg/funniest
Author: Ankit
Author-email: ankit@example.com
License: MIT
Platform: UNKNOWN
